<?xml version="1.0" encoding="UTF-8"?>
<TET>
<Page pageId="MCN1N808E7KFO" width="685" height="900">
<Font size="10.35">
<G t="B" x="383.26" y="611.33" w="6.91" h="10.35" />
<G t="ạ" x="390.16" y="611.33" w="5.76" h="10.35" />
<G t="n" x="395.92" y="611.33" w="5.76" h="10.35" />
<G t=" " x="401.68" y="611.33" w="2.88" h="10.35" />
<G t="c" x="404.42" y="611.33" w="5.18" h="10.35" />
<G t="ó" x="409.6" y="611.33" w="5.76" h="10.35" />
<G t=" " x="415.36" y="611.33" w="2.88" h="10.35" />
<G t="t" x="418.1" y="611.33" w="2.88" h="10.35" />
<G t="h" x="420.98" y="611.33" w="5.76" h="10.35" />
<G t="ể" x="426.74" y="611.33" w="5.76" h="10.35" />
<G t=" " x="432.49" y="611.33" w="2.88" h="10.35" />
<G t="đ" x="435.24" y="611.33" w="5.76" h="10.35" />
<G t="ạ" x="440.99" y="611.33" w="5.76" h="10.35" />
<G t="t" x="446.75" y="611.33" w="2.88" h="10.35" />
<G t=" " x="449.63" y="611.33" w="2.88" h="10.35" />
<G t="t" x="452.37" y="611.33" w="2.88" h="10.35" />
<G t="ớ" x="455.25" y="611.33" w="6.79" h="10.35" />
<G t="i" x="462.04" y="611.33" w="2.3" h="10.35" />
<G t=" " x="464.34" y="611.33" w="2.88" h="10.35" />
<G t="n" x="467.09" y="611.33" w="5.76" h="10.35" />
<G t="h" x="472.84" y="611.33" w="5.76" h="10.35" />
<G t="ữ" x="478.6" y="611.33" w="6.93" h="10.35" />
<G t="n" x="485.53" y="611.33" w="5.76" h="10.35" />
<G t="g" x="491.28" y="611.33" w="5.76" h="10.35" />
<G t=" " x="497.04" y="611.33" w="2.88" h="10.35" />
<G t="đ" x="499.79" y="611.33" w="5.76" h="10.35" />
<G t="ỉ" x="505.55" y="611.33" w="2.3" h="10.35" />
<G t="n" x="507.85" y="611.33" w="5.76" h="10.35" />
<G t="h" x="513.6" y="611.33" w="5.76" h="10.35" />
<G t=" " x="519.36" y="611.33" w="2.88" h="10.35" />
<G t="c" x="522.11" y="611.33" w="5.18" h="10.35" />
<G t="a" x="527.29" y="611.33" w="5.76" h="10.35" />
<G t="o" x="533.04" y="611.33" w="5.76" h="10.35" />
<G t=" " x="538.8" y="611.33" w="2.88" h="10.35" />
<G t="t" x="541.55" y="611.33" w="2.88" h="10.35" />
<G t="u" x="544.42" y="611.33" w="5.76" h="10.35" />
<G t="y" x="550.18" y="611.33" w="5.18" h="10.35" />
<G t="ệ" x="555.36" y="611.33" w="5.76" h="10.35" />
<G t="t" x="561.11" y="611.33" w="2.88" h="10.35" />
<G t=" " x="563.99" y="611.33" w="2.88" h="10.35" />
<G t="v" x="566.73" y="611.33" w="5.18" h="10.35" />
<G t="ờ" x="571.91" y="611.33" w="6.79" h="10.35" />
<G t="i" x="578.7" y="611.33" w="2.3" h="10.35" />
<G t=" " x="581" y="611.33" w="2.88" h="10.35" />
<G t="h" x="583.74" y="611.33" w="5.76" h="10.35" />
<G t="ơ" x="589.5" y="611.33" w="6.79" h="10.35" />
<G t="n" x="596.29" y="611.33" w="5.76" h="10.35" />
<G t=" " x="602.05" y="611.33" w="2.88" h="10.35" />
<G t="t" x="604.79" y="611.33" w="2.88" h="10.35" />
<G t="r" x="607.67" y="611.33" w="3.45" h="10.35" />
<G t="o" x="611.12" y="611.33" w="5.76" h="10.35" />
<G t="n" x="616.87" y="611.33" w="5.76" h="10.35" />
<G t="g" x="622.63" y="611.33" w="5.76" h="10.35" />
<G t=" " x="628.39" y="611.33" w="2.88" h="10.35" />
<G t="h" x="631.13" y="611.33" w="5.76" h="10.35" />
<G t="a" x="636.89" y="611.33" w="5.76" h="10.35" />
<G t="i" x="642.65" y="611.33" w="2.3" h="10.35" />
<G t=" " x="644.94" y="611.33" w="2.88" h="10.35" />
<G t="n" x="383.26" y="625.13" w="5.76" h="10.35" />
<G t="ă" x="389.01" y="625.13" w="5.76" h="10.35" />
<G t="m" x="394.77" y="625.13" w="8.62" h="10.35" />
<G t=" " x="403.4" y="625.13" w="2.88" h="10.35" />
<G t="m" x="405.62" y="625.13" w="8.62" h="10.35" />
<G t="à" x="414.25" y="625.13" w="5.76" h="10.35" />
<G t=" " x="420.01" y="625.13" w="2.88" h="10.35" />
<G t="b" x="422.23" y="625.13" w="5.76" h="10.35" />
<G t="ạ" x="427.99" y="625.13" w="5.76" h="10.35" />
<G t="n" x="433.75" y="625.13" w="5.76" h="10.35" />
<G t=" " x="439.5" y="625.13" w="2.88" h="10.35" />
<G t="d" x="441.73" y="625.13" w="5.76" h="10.35" />
<G t="à" x="447.49" y="625.13" w="5.76" h="10.35" />
<G t="n" x="453.25" y="625.13" w="5.76" h="10.35" />
<G t="h" x="459" y="625.13" w="5.76" h="10.35" />
<G t=" " x="464.76" y="625.13" w="2.88" h="10.35" />
<G t="đ" x="466.99" y="625.13" w="5.76" h="10.35" />
<G t="ể" x="472.74" y="625.13" w="5.76" h="10.35" />
<G t=" " x="478.5" y="625.13" w="2.88" h="10.35" />
<G t="t" x="480.73" y="625.13" w="2.88" h="10.35" />
<G t="h" x="483.61" y="625.13" w="5.76" h="10.35" />
<G t="e" x="489.36" y="625.13" w="5.76" h="10.35" />
<G t="o" x="495.12" y="625.13" w="5.76" h="10.35" />
<G t=" " x="500.87" y="625.13" w="2.88" h="10.35" />
<G t="đ" x="503.1" y="625.13" w="5.76" h="10.35" />
<G t="u" x="508.86" y="625.13" w="5.76" h="10.35" />
<G t="ổ" x="514.62" y="625.13" w="5.76" h="10.35" />
<G t="i" x="520.37" y="625.13" w="2.3" h="10.35" />
<G t=" " x="522.67" y="625.13" w="2.88" h="10.35" />
<G t="g" x="524.9" y="625.13" w="5.76" h="10.35" />
<G t="i" x="530.66" y="625.13" w="2.3" h="10.35" />
<G t="á" x="532.96" y="625.13" w="5.76" h="10.35" />
<G t="o" x="538.72" y="625.13" w="5.76" h="10.35" />
<G t=" " x="544.47" y="625.13" w="2.88" h="10.35" />
<G t="d" x="546.7" y="625.13" w="5.76" h="10.35" />
<G t="ụ" x="552.46" y="625.13" w="5.76" h="10.35" />
<G t="c" x="558.22" y="625.13" w="5.18" h="10.35" />
<G t=" " x="563.39" y="625.13" w="2.88" h="10.35" />
<G t="n" x="565.62" y="625.13" w="5.76" h="10.35" />
<G t="g" x="571.38" y="625.13" w="5.76" h="10.35" />
<G t="h" x="577.14" y="625.13" w="5.76" h="10.35" />
<G t="ề" x="582.89" y="625.13" w="5.76" h="10.35" />
<G t=" " x="588.65" y="625.13" w="2.88" h="10.35" />
<G t="n" x="590.88" y="625.13" w="5.76" h="10.35" />
<G t="g" x="596.64" y="625.13" w="5.76" h="10.35" />
<G t="h" x="602.39" y="625.13" w="5.76" h="10.35" />
<G t="i" x="608.15" y="625.13" w="2.3" h="10.35" />
<G t="ệ" x="610.45" y="625.13" w="5.76" h="10.35" />
<G t="p" x="616.21" y="625.13" w="5.76" h="10.35" />
<G t=" " x="621.96" y="625.13" w="2.88" h="10.35" />
<G t="t" x="624.2" y="625.13" w="2.88" h="10.35" />
<G t="h" x="627.08" y="625.13" w="5.76" h="10.35" />
<G t="ự" x="632.83" y="625.13" w="6.93" h="10.35" />
<G t="c" x="639.76" y="625.13" w="5.18" h="10.35" />
<G t=" " x="644.93" y="625.13" w="2.88" h="10.35" />
<G t="t" x="383.26" y="638.94" w="2.88" h="10.35" />
<G t="i" x="386.14" y="638.94" w="2.3" h="10.35" />
<G t="ễ" x="388.44" y="638.94" w="5.76" h="10.35" />
<G t="n" x="394.19" y="638.94" w="5.76" h="10.35" />
<G t=" " x="399.95" y="638.94" w="2.88" h="10.35" />
<G t="t" x="402.11" y="638.94" w="2.88" h="10.35" />
<G t="ạ" x="404.99" y="638.94" w="5.76" h="10.35" />
<G t="i" x="410.74" y="638.94" w="2.3" h="10.35" />
<G t=" " x="413.04" y="638.94" w="2.88" h="10.35" />
<G t="m" x="415.2" y="638.94" w="8.62" h="10.35" />
<G t="ộ" x="423.82" y="638.94" w="5.76" h="10.35" />
<G t="t" x="429.58" y="638.94" w="2.88" h="10.35" />
<G t=" " x="432.46" y="638.94" w="2.88" h="10.35" />
<G t="t" x="434.62" y="638.94" w="2.88" h="10.35" />
<G t="r" x="437.5" y="638.94" w="3.45" h="10.35" />
<G t="ư" x="440.94" y="638.94" w="6.93" h="10.35" />
<G t="ờ" x="447.87" y="638.94" w="6.79" h="10.35" />
<G t="n" x="454.66" y="638.94" w="5.76" h="10.35" />
<G t="g" x="460.42" y="638.94" w="5.76" h="10.35" />
<G t=" " x="466.17" y="638.94" w="2.88" h="10.35" />
<G t="c" x="468.33" y="638.94" w="5.18" h="10.35" />
<G t="a" x="473.51" y="638.94" w="5.76" h="10.35" />
<G t="o" x="479.27" y="638.94" w="5.76" h="10.35" />
<G t=" " x="485.02" y="638.94" w="2.88" h="10.35" />
<G t="đ" x="487.18" y="638.94" w="5.76" h="10.35" />
<G t="ẳ" x="492.94" y="638.94" w="5.76" h="10.35" />
<G t="n" x="498.7" y="638.94" w="5.76" h="10.35" />
<G t="g" x="504.45" y="638.94" w="5.76" h="10.35" />
<G t=" " x="510.21" y="638.94" w="2.88" h="10.35" />
<G t="s" x="512.37" y="638.94" w="5.18" h="10.35" />
<G t="o" x="517.55" y="638.94" w="5.76" h="10.35" />
<G t=" " x="523.31" y="638.94" w="2.88" h="10.35" />
<G t="v" x="525.47" y="638.94" w="5.18" h="10.35" />
<G t="ớ" x="530.64" y="638.94" w="6.79" h="10.35" />
<G t="i" x="537.43" y="638.94" w="2.3" h="10.35" />
<G t=" " x="539.73" y="638.94" w="2.88" h="10.35" />
<G t="t" x="541.89" y="638.94" w="2.88" h="10.35" />
<G t="r" x="544.77" y="638.94" w="3.45" h="10.35" />
<G t="ư" x="548.22" y="638.94" w="6.93" h="10.35" />
<G t="ờ" x="555.14" y="638.94" w="6.79" h="10.35" />
<G t="n" x="561.93" y="638.94" w="5.76" h="10.35" />
<G t="g" x="567.69" y="638.94" w="5.76" h="10.35" />
<G t=" " x="573.45" y="638.94" w="2.88" h="10.35" />
<G t="đ" x="575.61" y="638.94" w="5.76" h="10.35" />
<G t="ạ" x="581.36" y="638.94" w="5.76" h="10.35" />
<G t="i" x="587.12" y="638.94" w="2.3" h="10.35" />
<G t=" " x="589.42" y="638.94" w="2.88" h="10.35" />
<G t="h" x="591.58" y="638.94" w="5.76" h="10.35" />
<G t="ọ" x="597.34" y="638.94" w="5.76" h="10.35" />
<G t="c" x="603.09" y="638.94" w="5.18" h="10.35" />
<G t="." x="608.27" y="638.94" w="2.88" h="10.35" />
<G t="Đ" x="383.26" y="652.74" w="7.5" h="10.35" />
<G t="â" x="390.77" y="652.74" w="5.77" h="10.35" />
<G t="y" x="396.55" y="652.74" w="5.19" h="10.35" />
<G t=" " x="401.74" y="652.74" w="2.89" h="10.35" />
<G t="l" x="404.63" y="652.74" w="2.31" h="10.35" />
<G t="à" x="406.94" y="652.74" w="5.77" h="10.35" />
<G t=" " x="412.73" y="652.74" w="2.89" h="10.35" />
<G t="l" x="415.61" y="652.74" w="2.31" h="10.35" />
<G t="ý" x="417.93" y="652.74" w="5.19" h="10.35" />
<G t=" " x="423.12" y="652.74" w="2.89" h="10.35" />
<G t="d" x="426.01" y="652.74" w="5.77" h="10.35" />
<G t="o" x="431.79" y="652.74" w="5.77" h="10.35" />
<G t=" " x="437.58" y="652.74" w="2.89" h="10.35" />
<G t="t" x="440.46" y="652.74" w="2.89" h="10.35" />
<G t="ạ" x="443.35" y="652.74" w="5.77" h="10.35" />
<G t="i" x="449.13" y="652.74" w="2.31" h="10.35" />
<G t=" " x="451.45" y="652.74" w="2.89" h="10.35" />
<G t="s" x="454.34" y="652.74" w="5.19" h="10.35" />
<G t="a" x="459.54" y="652.74" w="5.77" h="10.35" />
<G t="o" x="465.32" y="652.74" w="5.77" h="10.35" />
<G t=" " x="471.11" y="652.74" w="2.89" h="10.35" />
<G t="t" x="473.99" y="652.74" w="2.89" h="10.35" />
<G t="r" x="476.88" y="652.74" w="3.46" h="10.35" />
<G t="ư" x="480.34" y="652.74" w="6.95" h="10.35" />
<G t="ờ" x="487.29" y="652.74" w="6.81" h="10.35" />
<G t="n" x="494.11" y="652.74" w="5.77" h="10.35" />
<G t="g" x="499.89" y="652.74" w="5.77" h="10.35" />
<G t=" " x="505.67" y="652.74" w="2.89" h="10.35" />
<G t="C" x="508.56" y="652.74" w="7.5" h="10.35" />
<G t="a" x="516.07" y="652.74" w="5.77" h="10.35" />
<G t="o" x="521.85" y="652.74" w="5.77" h="10.35" />
<G t=" " x="527.63" y="652.74" w="2.89" h="10.35" />
<G t="đ" x="530.52" y="652.74" w="5.77" h="10.35" />
<G t="ẳ" x="536.3" y="652.74" w="5.77" h="10.35" />
<G t="n" x="542.09" y="652.74" w="5.77" h="10.35" />
<G t="g" x="547.87" y="652.74" w="5.77" h="10.35" />
<G t=" " x="553.66" y="652.74" w="2.89" h="10.35" />
<G t="q" x="556.54" y="652.74" w="5.77" h="10.35" />
<G t="u" x="562.33" y="652.74" w="5.77" h="10.35" />
<G t="ả" x="568.11" y="652.74" w="5.77" h="10.35" />
<G t="n" x="573.89" y="652.74" w="5.77" h="10.35" />
<G t=" " x="579.68" y="652.74" w="2.89" h="10.35" />
<G t="t" x="582.56" y="652.74" w="2.89" h="10.35" />
<G t="r" x="585.45" y="652.74" w="3.46" h="10.35" />
<G t="ị" x="588.92" y="652.74" w="2.31" h="10.35" />
<G t=" " x="591.24" y="652.74" w="2.89" h="10.35" />
<G t="k" x="594.12" y="652.74" w="5.19" h="10.35" />
<G t="i" x="599.32" y="652.74" w="2.31" h="10.35" />
<G t="n" x="601.64" y="652.74" w="5.77" h="10.35" />
<G t="h" x="607.42" y="652.74" w="5.77" h="10.35" />
<G t=" " x="613.21" y="652.74" w="2.89" h="10.35" />
<G t="d" x="616.09" y="652.74" w="5.77" h="10.35" />
<G t="o" x="621.88" y="652.74" w="5.77" h="10.35" />
<G t="a" x="627.66" y="652.74" w="5.77" h="10.35" />
<G t="n" x="633.45" y="652.74" w="5.77" h="10.35" />
<G t="h" x="639.23" y="652.74" w="5.77" h="10.35" />
<G t=" " x="645" y="652.74" w="2.89" h="10.35" />
<G t="T" x="383.26" y="666.55" w="6.5" h="10.35" />
<G t="o" x="388.63" y="666.55" w="5.92" h="10.35" />
<G t="k" x="394.6" y="666.55" w="5.32" h="10.35" />
<G t="y" x="399.98" y="666.55" w="5.32" h="10.35" />
<G t="o" x="405.35" y="666.55" w="5.92" h="10.35" />
<G t=" " x="411.32" y="666.55" w="2.96" h="10.35" />
<G t="k" x="414.31" y="666.55" w="5.32" h="10.35" />
<G t="h" x="419.69" y="666.55" w="5.92" h="10.35" />
<G t="ô" x="425.66" y="666.55" w="5.92" h="10.35" />
<G t="n" x="431.63" y="666.55" w="5.92" h="10.35" />
<G t="g" x="437.6" y="666.55" w="5.92" h="10.35" />
<G t=" " x="443.57" y="666.55" w="2.96" h="10.35" />
<G t="n" x="446.56" y="666.55" w="5.92" h="10.35" />
<G t="g" x="452.53" y="666.55" w="5.92" h="10.35" />
<G t="ừ" x="458.5" y="666.55" w="7.12" h="10.35" />
<G t="n" x="465.67" y="666.55" w="5.92" h="10.35" />
<G t="g" x="471.64" y="666.55" w="5.92" h="10.35" />
<G t=" " x="477.61" y="666.55" w="2.96" h="10.35" />
<G t="p" x="480.6" y="666.55" w="5.92" h="10.35" />
<G t="h" x="486.57" y="666.55" w="5.92" h="10.35" />
<G t="á" x="492.55" y="666.55" w="5.92" h="10.35" />
<G t="t" x="498.52" y="666.55" w="2.96" h="10.35" />
<G t=" " x="501.53" y="666.55" w="2.96" h="10.35" />
<G t="t" x="504.52" y="666.55" w="2.96" h="10.35" />
<G t="r" x="507.53" y="666.55" w="3.54" h="10.35" />
<G t="i" x="511.13" y="666.55" w="2.36" h="10.35" />
<G t="ể" x="513.54" y="666.55" w="5.92" h="10.35" />
<G t="n" x="519.51" y="666.55" w="5.92" h="10.35" />
<G t=" " x="525.48" y="666.55" w="2.96" h="10.35" />
<G t="đ" x="528.47" y="666.55" w="5.92" h="10.35" />
<G t="ể" x="534.44" y="666.55" w="5.92" h="10.35" />
<G t=" " x="540.41" y="666.55" w="2.96" h="10.35" />
<G t="đ" x="543.4" y="666.55" w="5.92" h="10.35" />
<G t="á" x="549.38" y="666.55" w="5.92" h="10.35" />
<G t="p" x="555.35" y="666.55" w="5.92" h="10.35" />
<G t=" " x="561.32" y="666.55" w="2.96" h="10.35" />
<G t="ứ" x="564.31" y="666.55" w="7.12" h="10.35" />
<G t="n" x="571.48" y="666.55" w="5.92" h="10.35" />
<G t="g" x="577.45" y="666.55" w="5.92" h="10.35" />
<G t=" " x="583.42" y="666.55" w="2.96" h="10.35" />
<G t="n" x="586.41" y="666.55" w="5.92" h="10.35" />
<G t="h" x="592.38" y="666.55" w="5.92" h="10.35" />
<G t="u" x="598.35" y="666.55" w="5.92" h="10.35" />
<G t=" " x="604.32" y="666.55" w="2.96" h="10.35" />
<G t="c" x="607.31" y="666.55" w="5.32" h="10.35" />
<G t="ầ" x="612.69" y="666.55" w="5.92" h="10.35" />
<G t="u" x="618.66" y="666.55" w="5.92" h="10.35" />
<G t=" " x="624.63" y="666.55" w="2.96" h="10.35" />
<G t="c" x="627.62" y="666.55" w="5.32" h="10.35" />
<G t="ủ" x="632.99" y="666.55" w="5.92" h="10.35" />
<G t="a" x="638.96" y="666.55" w="5.92" h="10.35" />
<G t=" " x="644.88" y="666.55" w="2.96" h="10.35" />
<G t="s" x="383.26" y="680.35" w="5.18" h="10.35" />
<G t="i" x="388.44" y="680.35" w="2.3" h="10.35" />
<G t="n" x="390.73" y="680.35" w="5.76" h="10.35" />
<G t="h" x="396.49" y="680.35" w="5.76" h="10.35" />
<G t=" " x="402.25" y="680.35" w="2.88" h="10.35" />
<G t="v" x="404.41" y="680.35" w="5.18" h="10.35" />
<G t="i" x="409.58" y="680.35" w="2.3" h="10.35" />
<G t="ê" x="411.88" y="680.35" w="5.76" h="10.35" />
<G t="n" x="417.64" y="680.35" w="5.76" h="10.35" />
<G t="." x="423.4" y="680.35" w="2.88" h="10.35" />
<G t="V" x="383.26" y="694.16" w="6.91" h="10.35" />
<G t="à" x="390.16" y="694.16" w="5.76" h="10.35" />
<G t="o" x="395.92" y="694.16" w="5.76" h="10.35" />
<G t=" " x="401.68" y="694.16" w="2.88" h="10.35" />
<G t="n" x="403.68" y="694.16" w="5.76" h="10.35" />
<G t="ă" x="409.43" y="694.16" w="5.76" h="10.35" />
<G t="m" x="415.19" y="694.16" w="8.62" h="10.35" />
<G t=" " x="423.81" y="694.16" w="2.88" h="10.35" />
<G t="2" x="425.81" y="694.16" w="5.76" h="10.35" />
<G t="0" x="431.57" y="694.16" w="5.76" h="10.35" />
<G t="1" x="437.32" y="694.16" w="5.76" h="10.35" />
<G t="7" x="443.08" y="694.16" w="5.76" h="10.35" />
<G t="," x="448.84" y="694.16" w="2.88" h="10.35" />
<G t=" " x="451.71" y="694.16" w="2.88" h="10.35" />
<G t="n" x="453.71" y="694.16" w="5.76" h="10.35" />
<G t="g" x="459.47" y="694.16" w="5.76" h="10.35" />
<G t="o" x="465.23" y="694.16" w="5.76" h="10.35" />
<G t="à" x="470.98" y="694.16" w="5.76" h="10.35" />
<G t="i" x="476.74" y="694.16" w="2.3" h="10.35" />
<G t=" " x="479.04" y="694.16" w="2.88" h="10.35" />
<G t="g" x="481.04" y="694.16" w="5.76" h="10.35" />
<G t="i" x="486.8" y="694.16" w="2.3" h="10.35" />
<G t="ả" x="489.1" y="694.16" w="5.76" h="10.35" />
<G t="n" x="494.85" y="694.16" w="5.76" h="10.35" />
<G t="g" x="500.61" y="694.16" w="5.76" h="10.35" />
<G t=" " x="506.37" y="694.16" w="2.88" h="10.35" />
<G t="d" x="508.37" y="694.16" w="5.76" h="10.35" />
<G t="ạ" x="514.13" y="694.16" w="5.76" h="10.35" />
<G t="y" x="519.88" y="694.16" w="5.18" h="10.35" />
<G t=" " x="525.06" y="694.16" w="2.88" h="10.35" />
<G t="q" x="527.06" y="694.16" w="5.76" h="10.35" />
<G t="u" x="532.82" y="694.16" w="5.76" h="10.35" />
<G t="ả" x="538.57" y="694.16" w="5.76" h="10.35" />
<G t="n" x="544.33" y="694.16" w="5.76" h="10.35" />
<G t=" " x="550.09" y="694.16" w="2.88" h="10.35" />
<G t="t" x="552.09" y="694.16" w="2.88" h="10.35" />
<G t="r" x="554.97" y="694.16" w="3.45" h="10.35" />
<G t="ị" x="558.42" y="694.16" w="2.3" h="10.35" />
<G t=" " x="560.71" y="694.16" w="2.88" h="10.35" />
<G t="y" x="562.71" y="694.16" w="5.18" h="10.35" />
<G t=" " x="567.89" y="694.16" w="2.88" h="10.35" />
<G t="t" x="569.88" y="694.16" w="2.88" h="10.35" />
<G t="ế" x="572.76" y="694.16" w="5.76" h="10.35" />
<G t="," x="578.52" y="694.16" w="2.88" h="10.35" />
<G t=" " x="581.4" y="694.16" w="2.88" h="10.35" />
<G t="d" x="583.39" y="694.16" w="5.76" h="10.35" />
<G t="ị" x="589.15" y="694.16" w="2.3" h="10.35" />
<G t="c" x="591.45" y="694.16" w="5.18" h="10.35" />
<G t="h" x="596.62" y="694.16" w="5.76" h="10.35" />
<G t=" " x="602.38" y="694.16" w="2.88" h="10.35" />
<G t="v" x="604.38" y="694.16" w="5.18" h="10.35" />
<G t="ụ" x="609.56" y="694.16" w="5.76" h="10.35" />
<G t=" " x="615.31" y="694.16" w="2.88" h="10.35" />
<G t="k" x="617.31" y="694.16" w="5.18" h="10.35" />
<G t="h" x="622.49" y="694.16" w="5.76" h="10.35" />
<G t="á" x="628.25" y="694.16" w="5.76" h="10.35" />
<G t="c" x="634" y="694.16" w="5.18" h="10.35" />
<G t="h" x="639.18" y="694.16" w="5.76" h="10.35" />
<G t=" " x="644.93" y="694.16" w="2.88" h="10.35" />
<G t="h" x="383.26" y="707.96" w="5.7" h="10.35" />
<G t="à" x="388.94" y="707.96" w="5.7" h="10.35" />
<G t="n" x="394.63" y="707.96" w="5.7" h="10.35" />
<G t="g" x="400.31" y="707.96" w="5.7" h="10.35" />
<G t="," x="405.99" y="707.96" w="2.85" h="10.35" />
<G t=" " x="408.82" y="707.96" w="2.85" h="10.35" />
<G t="t" x="410.52" y="707.96" w="2.85" h="10.35" />
<G t="à" x="413.35" y="707.96" w="5.7" h="10.35" />
<G t="i" x="419.03" y="707.96" w="2.28" h="10.35" />
<G t=" " x="421.29" y="707.96" w="2.85" h="10.35" />
<G t="c" x="422.98" y="707.96" w="5.13" h="10.35" />
<G t="h" x="428.09" y="707.96" w="5.7" h="10.35" />
<G t="í" x="433.77" y="707.96" w="2.85" h="10.35" />
<G t="n" x="436.61" y="707.96" w="5.7" h="10.35" />
<G t="h" x="442.29" y="707.96" w="5.7" h="10.35" />
<G t=" " x="447.97" y="707.96" w="2.85" h="10.35" />
<G t="v" x="449.67" y="707.96" w="5.13" h="10.35" />
<G t="à" x="454.78" y="707.96" w="5.7" h="10.35" />
<G t=" " x="460.46" y="707.96" w="2.85" h="10.35" />
<G t="k" x="462.15" y="707.96" w="5.13" h="10.35" />
<G t="i" x="467.26" y="707.96" w="2.28" h="10.35" />
<G t="n" x="469.52" y="707.96" w="5.7" h="10.35" />
<G t="h" x="475.2" y="707.96" w="5.7" h="10.35" />
<G t=" " x="480.88" y="707.96" w="2.85" h="10.35" />
<G t="d" x="482.58" y="707.96" w="5.7" h="10.35" />
<G t="o" x="488.26" y="707.96" w="5.7" h="10.35" />
<G t="a" x="493.94" y="707.96" w="5.7" h="10.35" />
<G t="n" x="499.63" y="707.96" w="5.7" h="10.35" />
<G t="h" x="505.31" y="707.96" w="5.7" h="10.35" />
<G t="," x="511" y="707.96" w="2.85" h="10.35" />
<G t=" " x="513.83" y="707.96" w="2.85" h="10.35" />
<G t="c" x="515.52" y="707.96" w="5.13" h="10.35" />
<G t="h" x="520.63" y="707.96" w="5.7" h="10.35" />
<G t="ú" x="526.31" y="707.96" w="5.7" h="10.35" />
<G t="n" x="532" y="707.96" w="5.7" h="10.35" />
<G t="g" x="537.68" y="707.96" w="5.7" h="10.35" />
<G t=" " x="543.36" y="707.96" w="2.85" h="10.35" />
<G t="t" x="545.06" y="707.96" w="2.85" h="10.35" />
<G t="ô" x="547.89" y="707.96" w="5.7" h="10.35" />
<G t="i" x="553.57" y="707.96" w="2.28" h="10.35" />
<G t=" " x="555.83" y="707.96" w="2.85" h="10.35" />
<G t="s" x="557.52" y="707.96" w="5.13" h="10.35" />
<G t="ẽ" x="562.63" y="707.96" w="5.7" h="10.35" />
<G t=" " x="568.31" y="707.96" w="2.85" h="10.35" />
<G t="m" x="570.01" y="707.96" w="8.55" h="10.35" />
<G t="ở" x="578.53" y="707.96" w="6.73" h="10.35" />
<G t=" " x="585.24" y="707.96" w="2.85" h="10.35" />
<G t="r" x="586.93" y="707.96" w="3.42" h="10.35" />
<G t="ộ" x="590.33" y="707.96" w="5.7" h="10.35" />
<G t="n" x="596.01" y="707.96" w="5.7" h="10.35" />
<G t="g" x="601.7" y="707.96" w="5.7" h="10.35" />
<G t=" " x="607.38" y="707.96" w="2.85" h="10.35" />
<G t="c" x="609.07" y="707.96" w="5.13" h="10.35" />
<G t="h" x="614.18" y="707.96" w="5.7" h="10.35" />
<G t="ư" x="619.87" y="707.96" w="6.86" h="10.35" />
<G t="ơ" x="626.72" y="707.96" w="6.73" h="10.35" />
<G t="n" x="633.43" y="707.96" w="5.7" h="10.35" />
<G t="g" x="639.11" y="707.96" w="5.7" h="10.35" />
<G t=" " x="644.82" y="707.96" w="2.85" h="10.35" />
<G t="t" x="383.26" y="721.76" w="2.88" h="10.35" />
<G t="r" x="386.14" y="721.76" w="3.45" h="10.35" />
<G t="ì" x="389.58" y="721.76" w="2.88" h="10.35" />
<G t="n" x="392.46" y="721.76" w="5.76" h="10.35" />
<G t="h" x="398.22" y="721.76" w="5.76" h="10.35" />
<G t=" " x="403.98" y="721.76" w="2.88" h="10.35" />
<G t="s" x="406.13" y="721.76" w="5.18" h="10.35" />
<G t="a" x="411.31" y="721.76" w="5.76" h="10.35" />
<G t="n" x="417.07" y="721.76" w="5.76" h="10.35" />
<G t="g" x="422.82" y="721.76" w="5.76" h="10.35" />
<G t=" " x="428.58" y="721.76" w="2.88" h="10.35" />
<G t="c" x="430.74" y="721.76" w="5.18" h="10.35" />
<G t="ả" x="435.92" y="721.76" w="5.76" h="10.35" />
<G t=" " x="441.67" y="721.76" w="2.88" h="10.35" />
<G t="g" x="443.83" y="721.76" w="5.76" h="10.35" />
<G t="i" x="449.59" y="721.76" w="2.3" h="10.35" />
<G t="á" x="451.89" y="721.76" w="5.76" h="10.35" />
<G t="o" x="457.64" y="721.76" w="5.76" h="10.35" />
<G t=" " x="463.4" y="721.76" w="2.88" h="10.35" />
<G t="d" x="465.56" y="721.76" w="5.76" h="10.35" />
<G t="ụ" x="471.32" y="721.76" w="5.76" h="10.35" />
<G t="c" x="477.08" y="721.76" w="5.18" h="10.35" />
<G t=" " x="482.25" y="721.76" w="2.88" h="10.35" />
<G t="m" x="484.41" y="721.76" w="8.62" h="10.35" />
<G t="ầ" x="493.04" y="721.76" w="5.76" h="10.35" />
<G t="m" x="498.79" y="721.76" w="8.62" h="10.35" />
<G t=" " x="507.42" y="721.76" w="2.88" h="10.35" />
<G t="n" x="509.58" y="721.76" w="5.76" h="10.35" />
<G t="o" x="515.33" y="721.76" w="5.76" h="10.35" />
<G t="n" x="521.09" y="721.76" w="5.76" h="10.35" />
<G t="." x="526.85" y="721.76" w="2.88" h="10.35" />
<G t="L" x="383.26" y="735.57" w="5.76" h="10.35" />
<G t="à" x="389.01" y="735.57" w="5.76" h="10.35" />
<G t=" " x="394.77" y="735.57" w="2.88" h="10.35" />
<G t="n" x="396.75" y="735.57" w="5.76" h="10.35" />
<G t="g" x="402.5" y="735.57" w="5.76" h="10.35" />
<G t="ư" x="408.26" y="735.57" w="6.93" h="10.35" />
<G t="ờ" x="415.19" y="735.57" w="6.79" h="10.35" />
<G t="i" x="421.98" y="735.57" w="2.3" h="10.35" />
<G t=" " x="424.28" y="735.57" w="2.88" h="10.35" />
<G t="d" x="426.25" y="735.57" w="5.76" h="10.35" />
<G t="ẫ" x="432.01" y="735.57" w="5.76" h="10.35" />
<G t="n" x="437.76" y="735.57" w="5.76" h="10.35" />
<G t=" " x="443.52" y="735.57" w="2.88" h="10.35" />
<G t="đ" x="445.5" y="735.57" w="5.76" h="10.35" />
<G t="ầ" x="451.25" y="735.57" w="5.76" h="10.35" />
<G t="u" x="457.01" y="735.57" w="5.76" h="10.35" />
<G t=" " x="462.77" y="735.57" w="2.88" h="10.35" />
<G t="l" x="464.74" y="735.57" w="2.3" h="10.35" />
<G t="ĩ" x="467.04" y="735.57" w="2.88" h="10.35" />
<G t="n" x="469.92" y="735.57" w="5.76" h="10.35" />
<G t="h" x="475.67" y="735.57" w="5.76" h="10.35" />
<G t=" " x="481.43" y="735.57" w="2.88" h="10.35" />
<G t="v" x="483.41" y="735.57" w="5.18" h="10.35" />
<G t="ự" x="488.58" y="735.57" w="6.93" h="10.35" />
<G t="c" x="495.51" y="735.57" w="5.18" h="10.35" />
<G t=" " x="500.69" y="735.57" w="2.88" h="10.35" />
<G t="g" x="502.66" y="735.57" w="5.76" h="10.35" />
<G t="i" x="508.42" y="735.57" w="2.3" h="10.35" />
<G t="á" x="510.72" y="735.57" w="5.76" h="10.35" />
<G t="o" x="516.47" y="735.57" w="5.76" h="10.35" />
<G t=" " x="522.23" y="735.57" w="2.88" h="10.35" />
<G t="d" x="524.21" y="735.57" w="5.76" h="10.35" />
<G t="ụ" x="529.97" y="735.57" w="5.76" h="10.35" />
<G t="c" x="535.72" y="735.57" w="5.18" h="10.35" />
<G t=" " x="540.9" y="735.57" w="2.88" h="10.35" />
<G t="n" x="542.87" y="735.57" w="5.76" h="10.35" />
<G t="g" x="548.63" y="735.57" w="5.76" h="10.35" />
<G t="h" x="554.38" y="735.57" w="5.76" h="10.35" />
<G t="ề" x="560.14" y="735.57" w="5.76" h="10.35" />
<G t=" " x="565.9" y="735.57" w="2.88" h="10.35" />
<G t="n" x="567.88" y="735.57" w="5.76" h="10.35" />
<G t="g" x="573.63" y="735.57" w="5.76" h="10.35" />
<G t="h" x="579.39" y="735.57" w="5.76" h="10.35" />
<G t="i" x="585.15" y="735.57" w="2.3" h="10.35" />
<G t="ệ" x="587.44" y="735.57" w="5.76" h="10.35" />
<G t="p" x="593.2" y="735.57" w="5.76" h="10.35" />
<G t="," x="598.96" y="735.57" w="2.88" h="10.35" />
<G t=" " x="601.84" y="735.57" w="2.88" h="10.35" />
<G t="c" x="603.82" y="735.57" w="5.18" h="10.35" />
<G t="h" x="608.99" y="735.57" w="5.76" h="10.35" />
<G t="ú" x="614.75" y="735.57" w="5.76" h="10.35" />
<G t="n" x="620.51" y="735.57" w="5.76" h="10.35" />
<G t="g" x="626.26" y="735.57" w="5.76" h="10.35" />
<G t=" " x="632.02" y="735.57" w="2.88" h="10.35" />
<G t="t" x="634" y="735.57" w="2.88" h="10.35" />
<G t="ô" x="636.87" y="735.57" w="5.76" h="10.35" />
<G t="i" x="642.63" y="735.57" w="2.3" h="10.35" />
<G t=" " x="644.93" y="735.57" w="2.88" h="10.35" />
<G t="đ" x="383.26" y="749.37" w="5.7" h="10.35" />
<G t="à" x="388.94" y="749.37" w="5.7" h="10.35" />
<G t="o" x="394.62" y="749.37" w="5.7" h="10.35" />
<G t=" " x="400.31" y="749.37" w="2.85" h="10.35" />
<G t="t" x="402" y="749.37" w="2.85" h="10.35" />
<G t="ạ" x="404.83" y="749.37" w="5.7" h="10.35" />
<G t="o" x="410.51" y="749.37" w="5.7" h="10.35" />
<G t=" " x="416.2" y="749.37" w="2.85" h="10.35" />
<G t="r" x="417.89" y="749.37" w="3.42" h="10.35" />
<G t="a" x="421.29" y="749.37" w="5.7" h="10.35" />
<G t=" " x="426.97" y="749.37" w="2.85" h="10.35" />
<G t="c" x="428.66" y="749.37" w="5.13" h="10.35" />
<G t="á" x="433.77" y="749.37" w="5.7" h="10.35" />
<G t="c" x="439.45" y="749.37" w="5.13" h="10.35" />
<G t=" " x="444.56" y="749.37" w="2.85" h="10.35" />
<G t="s" x="446.25" y="749.37" w="5.13" h="10.35" />
<G t="i" x="451.36" y="749.37" w="2.28" h="10.35" />
<G t="n" x="453.62" y="749.37" w="5.7" h="10.35" />
<G t="h" x="459.3" y="749.37" w="5.7" h="10.35" />
<G t=" " x="464.99" y="749.37" w="2.85" h="10.35" />
<G t="v" x="466.68" y="749.37" w="5.13" h="10.35" />
<G t="i" x="471.79" y="749.37" w="2.28" h="10.35" />
<G t="ê" x="474.04" y="749.37" w="5.7" h="10.35" />
<G t="n" x="479.73" y="749.37" w="5.7" h="10.35" />
<G t=" " x="485.41" y="749.37" w="2.85" h="10.35" />
<G t="t" x="487.1" y="749.37" w="2.85" h="10.35" />
<G t="ố" x="489.93" y="749.37" w="5.7" h="10.35" />
<G t="t" x="495.62" y="749.37" w="2.85" h="10.35" />
<G t=" " x="498.45" y="749.37" w="2.85" h="10.35" />
<G t="n" x="500.14" y="749.37" w="5.7" h="10.35" />
<G t="g" x="505.82" y="749.37" w="5.7" h="10.35" />
<G t="h" x="511.51" y="749.37" w="5.7" h="10.35" />
<G t="i" x="517.19" y="749.37" w="2.28" h="10.35" />
<G t="ệ" x="519.45" y="749.37" w="5.7" h="10.35" />
<G t="p" x="525.13" y="749.37" w="5.7" h="10.35" />
<G t=" " x="530.81" y="749.37" w="2.85" h="10.35" />
<G t="đ" x="532.51" y="749.37" w="5.7" h="10.35" />
<G t="ư" x="538.19" y="749.37" w="6.86" h="10.35" />
<G t="ợ" x="545.04" y="749.37" w="6.73" h="10.35" />
<G t="c" x="551.75" y="749.37" w="5.13" h="10.35" />
<G t=" " x="556.86" y="749.37" w="2.85" h="10.35" />
<G t="t" x="558.55" y="749.37" w="2.85" h="10.35" />
<G t="r" x="561.38" y="749.37" w="3.42" h="10.35" />
<G t="a" x="564.78" y="749.37" w="5.7" h="10.35" />
<G t="n" x="570.46" y="749.37" w="5.7" h="10.35" />
<G t="g" x="576.14" y="749.37" w="5.7" h="10.35" />
<G t=" " x="581.83" y="749.37" w="2.85" h="10.35" />
<G t="b" x="583.52" y="749.37" w="5.7" h="10.35" />
<G t="ị" x="589.2" y="749.37" w="2.28" h="10.35" />
<G t=" " x="591.46" y="749.37" w="2.85" h="10.35" />
<G t="t" x="593.15" y="749.37" w="2.85" h="10.35" />
<G t="r" x="595.98" y="749.37" w="3.42" h="10.35" />
<G t="ì" x="599.38" y="749.37" w="2.85" h="10.35" />
<G t="n" x="602.21" y="749.37" w="5.7" h="10.35" />
<G t="h" x="607.89" y="749.37" w="5.7" h="10.35" />
<G t=" " x="613.58" y="749.37" w="2.85" h="10.35" />
<G t="đ" x="615.27" y="749.37" w="5.7" h="10.35" />
<G t="ộ" x="620.95" y="749.37" w="5.7" h="10.35" />
<G t=" " x="626.64" y="749.37" w="2.85" h="10.35" />
<G t="c" x="628.33" y="749.37" w="5.13" h="10.35" />
<G t="a" x="633.44" y="749.37" w="5.7" h="10.35" />
<G t="o" x="639.12" y="749.37" w="5.7" h="10.35" />
<G t=" " x="644.82" y="749.37" w="2.85" h="10.35" />
<G t="h" x="383.26" y="763.18" w="5.76" h="10.35" />
<G t="ơ" x="389.01" y="763.18" w="6.79" h="10.35" />
<G t="n" x="395.81" y="763.18" w="5.76" h="10.35" />
<G t=" " x="401.56" y="763.18" w="2.88" h="10.35" />
<G t="v" x="403.72" y="763.18" w="5.18" h="10.35" />
<G t="à" x="408.9" y="763.18" w="5.76" h="10.35" />
<G t=" " x="414.65" y="763.18" w="2.88" h="10.35" />
<G t="c" x="416.81" y="763.18" w="5.18" h="10.35" />
<G t="ả" x="421.99" y="763.18" w="5.76" h="10.35" />
<G t="i" x="427.75" y="763.18" w="2.3" h="10.35" />
<G t=" " x="430.05" y="763.18" w="2.88" h="10.35" />
<G t="t" x="432.21" y="763.18" w="2.88" h="10.35" />
<G t="h" x="435.08" y="763.18" w="5.76" h="10.35" />
<G t="i" x="440.84" y="763.18" w="2.3" h="10.35" />
<G t="ệ" x="443.14" y="763.18" w="5.76" h="10.35" />
<G t="n" x="448.9" y="763.18" w="5.76" h="10.35" />
<G t=" " x="454.65" y="763.18" w="2.88" h="10.35" />
<G t="k" x="456.81" y="763.18" w="5.18" h="10.35" />
<G t="h" x="461.99" y="763.18" w="5.76" h="10.35" />
<G t="ả" x="467.75" y="763.18" w="5.76" h="10.35" />
<G t=" " x="473.5" y="763.18" w="2.88" h="10.35" />
<G t="n" x="475.66" y="763.18" w="5.76" h="10.35" />
<G t="ă" x="481.42" y="763.18" w="5.76" h="10.35" />
<G t="n" x="487.18" y="763.18" w="5.76" h="10.35" />
<G t="g" x="492.93" y="763.18" w="5.76" h="10.35" />
<G t=" " x="498.69" y="763.18" w="2.88" h="10.35" />
<G t="đ" x="500.85" y="763.18" w="5.76" h="10.35" />
<G t="ư" x="506.61" y="763.18" w="6.93" h="10.35" />
<G t="ợ" x="513.54" y="763.18" w="6.79" h="10.35" />
<G t="c" x="520.33" y="763.18" w="5.18" h="10.35" />
<G t=" " x="525.5" y="763.18" w="2.88" h="10.35" />
<G t="t" x="527.67" y="763.18" w="2.88" h="10.35" />
<G t="u" x="530.54" y="763.18" w="5.76" h="10.35" />
<G t="y" x="536.3" y="763.18" w="5.18" h="10.35" />
<G t="ể" x="541.48" y="763.18" w="5.76" h="10.35" />
<G t="n" x="547.23" y="763.18" w="5.76" h="10.35" />
<G t=" " x="552.99" y="763.18" w="2.88" h="10.35" />
<G t="d" x="555.15" y="763.18" w="5.76" h="10.35" />
<G t="ụ" x="560.91" y="763.18" w="5.76" h="10.35" />
<G t="n" x="566.66" y="763.18" w="5.76" h="10.35" />
<G t="g" x="572.42" y="763.18" w="5.76" h="10.35" />
<G t="." x="578.17" y="763.18" w="2.88" h="10.35" />
<G t="T" x="383.26" y="776.98" w="6.33" h="10.35" />
<G t="ấ" x="389.58" y="776.98" w="5.76" h="10.35" />
<G t="t" x="395.34" y="776.98" w="2.88" h="10.35" />
<G t=" " x="398.22" y="776.98" w="2.88" h="10.35" />
<G t="c" x="399.95" y="776.98" w="5.18" h="10.35" />
<G t="ả" x="405.13" y="776.98" w="5.76" h="10.35" />
<G t=" " x="410.88" y="776.98" w="2.88" h="10.35" />
<G t="đ" x="412.62" y="776.98" w="5.76" h="10.35" />
<G t="ộ" x="418.37" y="776.98" w="5.76" h="10.35" />
<G t="i" x="424.13" y="776.98" w="2.3" h="10.35" />
<G t=" " x="426.43" y="776.98" w="2.88" h="10.35" />
<G t="n" x="428.16" y="776.98" w="5.76" h="10.35" />
<G t="g" x="433.92" y="776.98" w="5.76" h="10.35" />
<G t="ũ" x="439.67" y="776.98" w="5.76" h="10.35" />
<G t=" " x="445.43" y="776.98" w="2.88" h="10.35" />
<G t="n" x="447.17" y="776.98" w="5.76" h="10.35" />
<G t="h" x="452.92" y="776.98" w="5.76" h="10.35" />
<G t="â" x="458.68" y="776.98" w="5.76" h="10.35" />
<G t="n" x="464.44" y="776.98" w="5.76" h="10.35" />
<G t=" " x="470.19" y="776.98" w="2.88" h="10.35" />
<G t="v" x="471.93" y="776.98" w="5.18" h="10.35" />
<G t="i" x="477.1" y="776.98" w="2.3" h="10.35" />
<G t="ê" x="479.4" y="776.98" w="5.76" h="10.35" />
<G t="n" x="485.16" y="776.98" w="5.76" h="10.35" />
<G t=" " x="490.92" y="776.98" w="2.88" h="10.35" />
<G t="t" x="492.65" y="776.98" w="2.88" h="10.35" />
<G t="ạ" x="495.53" y="776.98" w="5.76" h="10.35" />
<G t="i" x="501.29" y="776.98" w="2.3" h="10.35" />
<G t=" " x="503.59" y="776.98" w="2.88" h="10.35" />
<G t="t" x="505.32" y="776.98" w="2.88" h="10.35" />
<G t="r" x="508.2" y="776.98" w="3.45" h="10.35" />
<G t="ư" x="511.65" y="776.98" w="6.93" h="10.35" />
<G t="ờ" x="518.57" y="776.98" w="6.79" h="10.35" />
<G t="n" x="525.36" y="776.98" w="5.76" h="10.35" />
<G t="g" x="531.12" y="776.98" w="5.76" h="10.35" />
<G t=" " x="536.88" y="776.98" w="2.88" h="10.35" />
<G t="C" x="538.61" y="776.98" w="7.48" h="10.35" />
<G t="a" x="546.09" y="776.98" w="5.76" h="10.35" />
<G t="o" x="551.85" y="776.98" w="5.76" h="10.35" />
<G t=" " x="557.6" y="776.98" w="2.88" h="10.35" />
<G t="đ" x="559.34" y="776.98" w="5.76" h="10.35" />
<G t="ẳ" x="565.1" y="776.98" w="5.76" h="10.35" />
<G t="n" x="570.85" y="776.98" w="5.76" h="10.35" />
<G t="g" x="576.61" y="776.98" w="5.76" h="10.35" />
<G t=" " x="582.36" y="776.98" w="2.88" h="10.35" />
<G t="q" x="584.1" y="776.98" w="5.76" h="10.35" />
<G t="u" x="589.86" y="776.98" w="5.76" h="10.35" />
<G t="ả" x="595.62" y="776.98" w="5.76" h="10.35" />
<G t="n" x="601.37" y="776.98" w="5.76" h="10.35" />
<G t=" " x="607.13" y="776.98" w="2.88" h="10.35" />
<G t="l" x="608.87" y="776.98" w="2.3" h="10.35" />
<G t="ý" x="611.17" y="776.98" w="5.18" h="10.35" />
<G t=" " x="616.34" y="776.98" w="2.88" h="10.35" />
<G t="T" x="617.89" y="776.98" w="6.33" h="10.35" />
<G t="o" x="623.07" y="776.98" w="5.76" h="10.35" />
<G t="k" x="628.82" y="776.98" w="5.18" h="10.35" />
<G t="y" x="634" y="776.98" w="5.18" h="10.35" />
<G t="o" x="639.18" y="776.98" w="5.76" h="10.35" />
<G t=" " x="644.93" y="776.98" w="2.88" h="10.35" />
<G t="c" x="383.26" y="790.79" w="5.18" h="10.35" />
<G t="ù" x="388.44" y="790.79" w="5.76" h="10.35" />
<G t="n" x="394.19" y="790.79" w="5.76" h="10.35" />
<G t="g" x="399.95" y="790.79" w="5.76" h="10.35" />
<G t=" " x="405.7" y="790.79" w="2.88" h="10.35" />
<G t="l" x="408.25" y="790.79" w="2.3" h="10.35" />
<G t="à" x="410.55" y="790.79" w="5.76" h="10.35" />
<G t="m" x="416.31" y="790.79" w="8.62" h="10.35" />
<G t=" " x="424.93" y="790.79" w="2.88" h="10.35" />
<G t="v" x="427.47" y="790.79" w="5.18" h="10.35" />
<G t="i" x="432.65" y="790.79" w="2.3" h="10.35" />
<G t="ệ" x="434.95" y="790.79" w="5.76" h="10.35" />
<G t="c" x="440.71" y="790.79" w="5.18" h="10.35" />
<G t=" " x="445.88" y="790.79" w="2.88" h="10.35" />
<G t="đ" x="448.43" y="790.79" w="5.76" h="10.35" />
<G t="ể" x="454.18" y="790.79" w="5.76" h="10.35" />
<G t=" " x="459.94" y="790.79" w="2.88" h="10.35" />
<G t="c" x="462.48" y="790.79" w="5.18" h="10.35" />
<G t="u" x="467.66" y="790.79" w="5.76" h="10.35" />
<G t="n" x="473.42" y="790.79" w="5.76" h="10.35" />
<G t="g" x="479.17" y="790.79" w="5.76" h="10.35" />
<G t=" " x="484.93" y="790.79" w="2.88" h="10.35" />
<G t="c" x="487.48" y="790.79" w="5.18" h="10.35" />
<G t="ấ" x="492.65" y="790.79" w="5.76" h="10.35" />
<G t="p" x="498.41" y="790.79" w="5.76" h="10.35" />
<G t=" " x="504.17" y="790.79" w="2.88" h="10.35" />
<G t="n" x="506.71" y="790.79" w="5.76" h="10.35" />
<G t="ề" x="512.47" y="790.79" w="5.76" h="10.35" />
<G t="n" x="518.22" y="790.79" w="5.76" h="10.35" />
<G t=" " x="523.98" y="790.79" w="2.88" h="10.35" />
<G t="g" x="526.53" y="790.79" w="5.76" h="10.35" />
<G t="i" x="532.28" y="790.79" w="2.3" h="10.35" />
<G t="á" x="534.58" y="790.79" w="5.76" h="10.35" />
<G t="o" x="540.34" y="790.79" w="5.76" h="10.35" />
<G t=" " x="546.09" y="790.79" w="2.88" h="10.35" />
<G t="d" x="548.64" y="790.79" w="5.76" h="10.35" />
<G t="ụ" x="554.4" y="790.79" w="5.76" h="10.35" />
<G t="c" x="560.15" y="790.79" w="5.18" h="10.35" />
<G t=" " x="565.33" y="790.79" w="2.88" h="10.35" />
<G t="k" x="567.87" y="790.79" w="5.18" h="10.35" />
<G t="h" x="573.05" y="790.79" w="5.76" h="10.35" />
<G t="ô" x="578.81" y="790.79" w="5.76" h="10.35" />
<G t="n" x="584.56" y="790.79" w="5.76" h="10.35" />
<G t="g" x="590.32" y="790.79" w="5.76" h="10.35" />
<G t=" " x="596.08" y="790.79" w="2.88" h="10.35" />
<G t="g" x="598.62" y="790.79" w="5.76" h="10.35" />
<G t="i" x="604.38" y="790.79" w="2.3" h="10.35" />
<G t="ố" x="606.68" y="790.79" w="5.76" h="10.35" />
<G t="n" x="612.43" y="790.79" w="5.76" h="10.35" />
<G t="g" x="618.19" y="790.79" w="5.76" h="10.35" />
<G t=" " x="623.95" y="790.79" w="2.88" h="10.35" />
<G t="n" x="626.5" y="790.79" w="5.76" h="10.35" />
<G t="h" x="632.25" y="790.79" w="5.76" h="10.35" />
<G t="ư" x="638.01" y="790.79" w="6.93" h="10.35" />
<G t=" " x="644.94" y="790.79" w="2.88" h="10.35" />
<G t="b" x="383.26" y="804.59" w="5.84" h="10.35" />
<G t="ấ" x="389.13" y="804.59" w="5.84" h="10.35" />
<G t="t" x="395" y="804.59" w="2.92" h="10.35" />
<G t=" " x="397.94" y="804.59" w="2.92" h="10.35" />
<G t="k" x="400.87" y="804.59" w="5.25" h="10.35" />
<G t="ỳ" x="406.16" y="804.59" w="5.25" h="10.35" />
<G t=" " x="411.44" y="804.59" w="2.92" h="10.35" />
<G t="n" x="414.37" y="804.59" w="5.84" h="10.35" />
<G t="ơ" x="420.25" y="804.59" w="6.89" h="10.35" />
<G t="i" x="427.16" y="804.59" w="2.33" h="10.35" />
<G t=" " x="429.52" y="804.59" w="2.92" h="10.35" />
<G t="n" x="432.45" y="804.59" w="5.84" h="10.35" />
<G t="à" x="438.32" y="804.59" w="5.84" h="10.35" />
<G t="o" x="444.2" y="804.59" w="5.84" h="10.35" />
<G t=" " x="450.07" y="804.59" w="2.92" h="10.35" />
<G t="k" x="453" y="804.59" w="5.25" h="10.35" />
<G t="h" x="458.28" y="804.59" w="5.84" h="10.35" />
<G t="á" x="464.15" y="804.59" w="5.84" h="10.35" />
<G t="c" x="470.03" y="804.59" w="5.25" h="10.35" />
<G t="," x="475.31" y="804.59" w="2.92" h="10.35" />
<G t=" " x="478.25" y="804.59" w="2.92" h="10.35" />
<G t="p" x="481.18" y="804.59" w="5.84" h="10.35" />
<G t="h" x="487.05" y="804.59" w="5.84" h="10.35" />
<G t="ả" x="492.93" y="804.59" w="5.84" h="10.35" />
<G t="n" x="498.8" y="804.59" w="5.84" h="10.35" />
<G t=" " x="504.67" y="804.59" w="2.92" h="10.35" />
<G t="á" x="507.6" y="804.59" w="5.84" h="10.35" />
<G t="n" x="513.47" y="804.59" w="5.84" h="10.35" />
<G t="h" x="519.35" y="804.59" w="5.84" h="10.35" />
<G t=" " x="525.22" y="804.59" w="2.92" h="10.35" />
<G t="c" x="528.15" y="804.59" w="5.25" h="10.35" />
<G t="a" x="533.43" y="804.59" w="5.84" h="10.35" />
<G t="m" x="539.3" y="804.59" w="8.75" h="10.35" />
<G t=" " x="548.09" y="804.59" w="2.92" h="10.35" />
<G t="k" x="551.02" y="804.59" w="5.25" h="10.35" />
<G t="ế" x="556.3" y="804.59" w="5.84" h="10.35" />
<G t="t" x="562.17" y="804.59" w="2.92" h="10.35" />
<G t=" " x="565.11" y="804.59" w="2.92" h="10.35" />
<G t="c" x="568.04" y="804.59" w="5.25" h="10.35" />
<G t="ủ" x="573.33" y="804.59" w="5.84" h="10.35" />
<G t="a" x="579.2" y="804.59" w="5.84" h="10.35" />
<G t=" " x="585.07" y="804.59" w="2.92" h="10.35" />
<G t="c" x="588" y="804.59" w="5.25" h="10.35" />
<G t="h" x="593.29" y="804.59" w="5.84" h="10.35" />
<G t="ú" x="599.16" y="804.59" w="5.84" h="10.35" />
<G t="n" x="605.03" y="804.59" w="5.84" h="10.35" />
<G t="g" x="610.9" y="804.59" w="5.84" h="10.35" />
<G t=" " x="616.77" y="804.59" w="2.92" h="10.35" />
<G t="t" x="619.71" y="804.59" w="2.92" h="10.35" />
<G t="ô" x="622.65" y="804.59" w="5.84" h="10.35" />
<G t="i" x="628.52" y="804.59" w="2.33" h="10.35" />
<G t=" " x="630.88" y="804.59" w="2.92" h="10.35" />
<G t="v" x="633.81" y="804.59" w="5.25" h="10.35" />
<G t="ề" x="639.1" y="804.59" w="5.84" h="10.35" />
<G t=" " x="644.94" y="804.59" w="2.92" h="10.35" />
<G t="t" x="383.26" y="818.4" w="2.88" h="10.35" />
<G t="ư" x="386.14" y="818.4" w="6.93" h="10.35" />
<G t="ơ" x="393.06" y="818.4" w="6.79" h="10.35" />
<G t="n" x="399.85" y="818.4" w="5.76" h="10.35" />
<G t="g" x="405.61" y="818.4" w="5.76" h="10.35" />
<G t=" " x="411.37" y="818.4" w="2.88" h="10.35" />
<G t="l" x="413.53" y="818.4" w="2.3" h="10.35" />
<G t="a" x="415.83" y="818.4" w="5.76" h="10.35" />
<G t="i" x="421.58" y="818.4" w="2.3" h="10.35" />
<G t=" " x="423.88" y="818.4" w="2.88" h="10.35" />
<G t="c" x="426.04" y="818.4" w="5.18" h="10.35" />
<G t="ủ" x="431.22" y="818.4" w="5.76" h="10.35" />
<G t="a" x="436.98" y="818.4" w="5.76" h="10.35" />
<G t=" " x="442.73" y="818.4" w="2.88" h="10.35" />
<G t="s" x="444.89" y="818.4" w="5.18" h="10.35" />
<G t="i" x="450.07" y="818.4" w="2.3" h="10.35" />
<G t="n" x="452.37" y="818.4" w="5.76" h="10.35" />
<G t="h" x="458.13" y="818.4" w="5.76" h="10.35" />
<G t=" " x="463.88" y="818.4" w="2.88" h="10.35" />
<G t="v" x="466.04" y="818.4" w="5.18" h="10.35" />
<G t="i" x="471.22" y="818.4" w="2.3" h="10.35" />
<G t="ê" x="473.52" y="818.4" w="5.76" h="10.35" />
<G t="n" x="479.28" y="818.4" w="5.76" h="10.35" />
<G t="." x="485.03" y="818.4" w="2.88" h="10.35" />
</Font>
<Font size="13.7">
<G t="T" x="383.26" y="592.6" w="7.97" h="13.7" />
<G t="r" x="390.51" y="592.6" w="5.07" h="13.7" />
<G t="ư" x="395.58" y="592.6" w="9.44" h="13.7" />
<G t="ờ" x="405.02" y="592.6" w="9.27" h="13.7" />
<G t="n" x="414.3" y="592.6" w="7.97" h="13.7" />
<G t="g" x="422.27" y="592.6" w="7.97" h="13.7" />
<G t=" " x="430.24" y="592.6" w="3.63" h="13.7" />
<G t="c" x="433.86" y="592.6" w="7.25" h="13.7" />
<G t="a" x="441.12" y="592.6" w="7.25" h="13.7" />
<G t="o" x="448.37" y="592.6" w="7.97" h="13.7" />
<G t=" " x="456.34" y="592.6" w="3.63" h="13.7" />
<G t="đ" x="459.96" y="592.6" w="7.97" h="13.7" />
<G t="ẳ" x="467.93" y="592.6" w="7.25" h="13.7" />
<G t="n" x="475.19" y="592.6" w="7.97" h="13.7" />
<G t="g" x="483.16" y="592.6" w="7.97" h="13.7" />
<G t=" " x="491.12" y="592.6" w="3.63" h="13.7" />
<G t="v" x="494.75" y="592.6" w="7.25" h="13.7" />
<G t="ì" x="502" y="592.6" w="3.63" h="13.7" />
<G t=" " x="505.63" y="592.6" w="3.63" h="13.7" />
<G t="t" x="509.26" y="592.6" w="4.34" h="13.7" />
<G t="ư" x="513.6" y="592.6" w="9.44" h="13.7" />
<G t="ơ" x="523.04" y="592.6" w="9.27" h="13.7" />
<G t="n" x="532.32" y="592.6" w="7.97" h="13.7" />
<G t="g" x="540.29" y="592.6" w="7.97" h="13.7" />
<G t=" " x="548.26" y="592.6" w="3.63" h="13.7" />
<G t="l" x="551.88" y="592.6" w="3.63" h="13.7" />
<G t="a" x="555.51" y="592.6" w="7.25" h="13.7" />
<G t="i" x="562.76" y="592.6" w="3.63" h="13.7" />
<G t=" " x="566.39" y="592.6" w="3.63" h="13.7" />
<G t="c" x="570.01" y="592.6" w="7.25" h="13.7" />
<G t="ủ" x="577.26" y="592.6" w="7.97" h="13.7" />
<G t="a" x="585.23" y="592.6" w="7.25" h="13.7" />
<G t=" " x="592.49" y="592.6" w="3.63" h="13.7" />
<G t="b" x="596.11" y="592.6" w="7.97" h="13.7" />
<G t="ạ" x="604.08" y="592.6" w="7.25" h="13.7" />
<G t="n" x="611.33" y="592.6" w="7.97" h="13.7" />
</Font>
<Font size="8.15">
<G t="C" x="495.11" y="879.36" w="5.89" h="8.15" />
<G t="a" x="501" y="879.36" w="4.53" h="8.15" />
<G t="o" x="505.53" y="879.36" w="4.98" h="8.15" />
<G t=" " x="510.51" y="879.36" w="2.27" h="8.15" />
<G t="đ" x="512.21" y="879.36" w="4.98" h="8.15" />
<G t="ẳ" x="517.19" y="879.36" w="4.53" h="8.15" />
<G t="n" x="521.72" y="879.36" w="4.98" h="8.15" />
<G t="g" x="526.7" y="879.36" w="4.98" h="8.15" />
<G t=" " x="531.68" y="879.36" w="2.27" h="8.15" />
<G t="q" x="533.38" y="879.36" w="4.98" h="8.15" />
<G t="u" x="538.36" y="879.36" w="4.98" h="8.15" />
<G t="ả" x="543.34" y="879.36" w="4.53" h="8.15" />
<G t="n" x="547.88" y="879.36" w="4.98" h="8.15" />
<G t=" " x="552.86" y="879.36" w="2.27" h="8.15" />
<G t="t" x="554.56" y="879.36" w="2.71" h="8.15" />
<G t="r" x="557.27" y="879.36" w="3.17" h="8.15" />
<G t="ị" x="560.44" y="879.36" w="2.27" h="8.15" />
<G t=" " x="562.71" y="879.36" w="2.27" h="8.15" />
<G t="k" x="564.41" y="879.36" w="4.53" h="8.15" />
<G t="i" x="568.94" y="879.36" w="2.27" h="8.15" />
<G t="n" x="571.21" y="879.36" w="4.98" h="8.15" />
<G t="h" x="576.19" y="879.36" w="4.98" h="8.15" />
<G t=" " x="581.17" y="879.36" w="2.27" h="8.15" />
<G t="d" x="582.87" y="879.36" w="4.98" h="8.15" />
<G t="o" x="587.85" y="879.36" w="4.98" h="8.15" />
<G t="a" x="592.83" y="879.36" w="4.53" h="8.15" />
<G t="n" x="597.36" y="879.36" w="4.98" h="8.15" />
<G t="h" x="602.34" y="879.36" w="4.98" h="8.15" />
<G t=" " x="607.32" y="879.36" w="2.27" h="8.15" />
<G t="T" x="609.02" y="879.36" w="4.98" h="8.15" />
<G t="o" x="613.7" y="879.36" w="4.98" h="8.15" />
<G t="k" x="618.68" y="879.36" w="4.53" h="8.15" />
<G t="y" x="623.21" y="879.36" w="4.53" h="8.15" />
<G t="o" x="627.75" y="879.36" w="4.98" h="8.15" />
</Font>
<Font size="6.28">
<G t="G" x="674.31" y="321.6" w="8.15" h="6.28" />
</Font>
<Font size="2.24">
<G t="I" x="674.31" y="327.88" w="8.15" h="2.24" />
</Font>
<Font size="5.83">
<G t="Á" x="674.31" y="330.12" w="8.15" h="5.83" />
</Font>
<Font size="6.28">
<G t="O" x="674.31" y="335.95" w="8.15" h="6.28" />
</Font>
<Font size="2.24">
<G t=" " x="674.31" y="342.23" w="8.15" h="2.24" />
</Font>
<Font size="5.83">
<G t="D" x="674.31" y="343.91" w="8.15" h="5.83" />
<G t="Ụ" x="674.31" y="349.74" w="8.15" h="5.83" />
<G t="C" x="674.31" y="355.57" w="8.15" h="5.83" />
</Font>
<Font size="2.24">
<G t=" " x="674.31" y="361.39" w="8.15" h="2.24" />
</Font>
<Font size="5.83">
<G t="Đ" x="674.31" y="363.07" w="8.15" h="5.83" />
<G t="Ạ" x="674.31" y="368.9" w="8.15" h="5.83" />
</Font>
<Font size="2.24">
<G t="I" x="674.31" y="374.73" w="8.15" h="2.24" />
<G t=" " x="674.31" y="376.97" w="8.15" h="2.24" />
</Font>
<Font size="5.83">
<G t="H" x="674.31" y="378.65" w="8.15" h="5.83" />
</Font>
<Font size="6.28">
<G t="Ọ" x="674.31" y="384.48" w="8.15" h="6.28" />
</Font>
<Font size="5.83">
<G t="C" x="674.31" y="390.76" w="8.15" h="5.83" />
</Font>
<Font size="13.86">
<G t="w" x="510.24" y="839.26" w="9.42" h="13.86" />
<G t="w" x="519.83" y="839.26" w="9.42" h="13.86" />
<G t="w" x="529.42" y="839.26" w="9.42" h="13.86" />
<G t="." x="538.1" y="839.26" w="3.64" h="13.86" />
<G t="t" x="541.74" y="839.26" w="4.43" h="13.86" />
<G t="o" x="546.08" y="839.26" w="6.82" h="13.86" />
<G t="k" x="552.86" y="839.26" w="6.76" h="13.86" />
<G t="y" x="559.51" y="839.26" w="6.5" h="13.86" />
<G t="o" x="566.05" y="839.26" w="6.82" h="13.86" />
<G t="-" x="572.87" y="839.26" w="4.71" h="13.86" />
<G t="k" x="577.58" y="839.26" w="6.76" h="13.86" />
<G t="e" x="584.3" y="839.26" w="5.79" h="13.86" />
<G t="i" x="590.22" y="839.26" w="4.09" h="13.86" />
<G t="t" x="594.17" y="839.26" w="4.43" h="13.86" />
<G t="a" x="598.51" y="839.26" w="7.19" h="13.86" />
<G t="n" x="605.53" y="839.26" w="7.61" h="13.86" />
<G t="." x="613.14" y="839.26" w="3.64" h="13.86" />
<G t="a" x="616.79" y="839.26" w="7.19" h="13.86" />
<G t="c" x="623.91" y="839.26" w="5.53" h="13.86" />
<G t="." x="629.38" y="839.26" w="3.64" h="13.86" />
<G t="j" x="633.03" y="839.26" w="3.99" h="13.86" />
<G t="p" x="637.02" y="839.26" w="7.11" h="13.86" />
</Font>
<Font size="8.15">
<G t="1" x="651.46" y="879.28" w="4.49" h="8.15" />
<G t="9" x="655.94" y="879.28" w="4.49" h="8.15" />
</Font>
</Page>
</TET>
